JupyterChatbook/Chatbook.py
JupyterChatbook/__init__.py
JupyterChatbook-0.0.16.dist-info/LICENSE
JupyterChatbook-0.0.16.dist-info/METADATA
JupyterChatbook-0.0.16.dist-info/WHEEL
JupyterChatbook-0.0.16.dist-info/top_level.txt
JupyterChatbook-0.0.16.dist-info/RECORD
