Metadata-Version: 2.1
Name: JupyterChatbook
Version: 0.0.16
Summary: Custom Jupyter magics for interacting with LLMs.
Home-page: https://github.com/antononcube/Python-JupyterChatbook
Author: Anton Antonov
Author-email: antononcube@posteo.net
Keywords: llm,llm prompt,chat object,chatbook,magic,magics,jupyter,notebook
Classifier: Intended Audience :: Science/Research
Classifier: Intended Audience :: Developers
Classifier: Programming Language :: Python :: 3
Classifier: License :: OSI Approved :: BSD License
Classifier: Intended Audience :: Science/Research
Classifier: Intended Audience :: Developers
Classifier: Operating System :: OS Independent
Requires-Python: >=3.7
License-File: LICENSE
Requires-Dist: LLMFunctionObjects >=0.1.3
Requires-Dist: LLMPrompts >=0.1.2
Requires-Dist: IPython >=8.15.0
Requires-Dist: pyperclip >=1.8.2
Requires-Dist: google-generativeai >=0.2.0
Requires-Dist: openai >=0.28.1
